comrade/connections.py
comrade/elasticsearch_assets.py
comrade/index.py
comrade/blueprints/__init__.py
comrade/blueprints/alias.py
comrade/blueprints/cluster.py
comrade/blueprints/index.py
comrade/blueprints/node.py
comrade/blueprints/rest.py
comrade/blueprints/snapshot.py
comrade/blueprints/task.py
comrade/blueprints/template.py
comrade/blueprints/views.py
comrade/static/favicon.ico
comrade/static/index.html
comrade/static/manifest.json
comrade/static/robots.txt
comrade/static/css/app.5d292c8a.css
comrade/static/css/chunk-vendors.f07fc4cd.css
comrade/static/css/snapshots.9593f1fa.css
comrade/static/favicons/green/android-icon-144x144.png
comrade/static/favicons/green/android-icon-192x192.png
comrade/static/favicons/green/android-icon-36x36.png
comrade/static/favicons/green/android-icon-48x48.png
comrade/static/favicons/green/android-icon-72x72.png
comrade/static/favicons/green/android-icon-96x96.png
comrade/static/favicons/green/apple-icon-114x114.png
comrade/static/favicons/green/apple-icon-120x120.png
comrade/static/favicons/green/apple-icon-144x144.png
comrade/static/favicons/green/apple-icon-152x152.png
comrade/static/favicons/green/apple-icon-180x180.png
comrade/static/favicons/green/apple-icon-57x57.png
comrade/static/favicons/green/apple-icon-60x60.png
comrade/static/favicons/green/apple-icon-72x72.png
comrade/static/favicons/green/apple-icon-76x76.png
comrade/static/favicons/green/apple-icon-precomposed.png
comrade/static/favicons/green/apple-icon.png
comrade/static/favicons/green/browserconfig.xml
comrade/static/favicons/green/favicon-16x16.png
comrade/static/favicons/green/favicon-32x32.png
comrade/static/favicons/green/favicon-96x96.png
comrade/static/favicons/green/favicon.ico
comrade/static/favicons/green/green.png
comrade/static/favicons/green/manifest.json
comrade/static/favicons/green/ms-icon-144x144.png
comrade/static/favicons/green/ms-icon-150x150.png
comrade/static/favicons/green/ms-icon-310x310.png
elasticsearch_comrade-1.2.0.dist-info/METADATA
elasticsearch_comrade-1.2.0.dist-info/WHEEL
elasticsearch_comrade-1.2.0.dist-info/entry_points.txt
elasticsearch_comrade-1.2.0.dist-info/top_level.txt
elasticsearch_comrade-1.2.0.dist-info/RECORD
