Metadata-Version: 2.1
Name: elasticsearch-comrade
Version: 1.2.0
Summary: Elasticsearch admin panel built for ops and monitoring
Home-page: UNKNOWN
Author: Moshe Zada
Author-email: UNKNOWN
License: UNKNOWN
Platform: UNKNOWN
Requires-Dist: sanic
Requires-Dist: ujson
Requires-Dist: elasticsearch-async
Requires-Dist: click
